MANIFEST.in
README.rst
setup.cfg
setup.py
platformer/__init__.py
platformer/gradient.py
platformer/level.py
platformer/physics.py
platformer/player.py
platformer/sprites/heroine/default.png
platformer/sprites/heroine/fall.png
platformer/sprites/heroine/walk.png
platformer/sprites/heroine/wall_1.png
platformer/sprites/heroine/wall_2.png
platformer_game.egg-info/PKG-INFO
platformer_game.egg-info/SOURCES.txt
platformer_game.egg-info/dependency_links.txt
platformer_game.egg-info/entry_points.txt
platformer_game.egg-info/requires.txt
platformer_game.egg-info/top_level.txt