Metadata-Version: 1.1
Name: platformer-game
Version: 0.1.1
Summary: atmospheric platformer game
Home-page: UNKNOWN
Author: Tobias Bengfort
Author-email: tobias.bengfort@gmx.net
License: GPLv3+
Platform: UNKNOWN
Classifier: Development Status :: 4 - Beta
Classifier: Intended Audience :: End Users/Desktop
Classifier: Operating System :: OS Independent
Classifier: Programming Language :: Python
Classifier: License :: OSI Approved :: GNU General Public License v3 or later (GPLv3+)
Classifier: Topic :: Games/Entertainment :: Side-Scrolling/Arcade Games
